mptt_reader/__init__.py
mptt_reader/constants.py
mptt_reader/logger.py
mptt_reader/reader.py
mptt_reader-1.0.2.dist-info/LICENSE
mptt_reader-1.0.2.dist-info/METADATA
mptt_reader-1.0.2.dist-info/WHEEL
mptt_reader-1.0.2.dist-info/top_level.txt
mptt_reader-1.0.2.dist-info/RECORD
