Metadata-Version: 2.1
Name: mptt-reader
Version: 1.0.2
Summary: A framework for easily logging and modifying Tristar-MPTT-45 Solar Controllers over a serial connection.
Author-email: Calastrophe <vmxoperation@proton.me>
Project-URL: Homepage, https://github.com/Calastrophe/mptt-reader
Project-URL: Bug Tracker, https://github.com/Calastrophe/mptt-reader/issues
Classifier: Programming Language :: Python :: 3.10
Classifier: License :: OSI Approved :: GNU General Public License v3 (GPLv3)
Classifier: Operating System :: OS Independent
Requires-Python: >=3.10
License-File: LICENSE
Requires-Dist: pymodbus
Requires-Dist: pyserial
Requires-Dist: continuous-threading
